[
    {
        "filename": "不破不立：哪吒之魔童鬧海幕後紀錄片 (2025) - 2160p.WEB-DL.H265.10bit.DDP2.0.mkv",
        "absolute_path": "H:\\共用雲端硬碟\\@LiangTsaoEmby_本月更新\\電影\\不破不立：哪吒之魔童鬧海幕後紀錄片 (2025)\\不破不立：哪吒之魔童鬧海幕後紀錄片 (2025) - 2160p.WEB-DL.H265.10bit.DDP2.0.mkv",
        "relative_path": "@LiangTsaoEmby_本月更新\\電影\\不破不立：哪吒之魔童鬧海幕後紀錄片 (2025)\\不破不立：哪吒之魔童鬧海幕後紀錄片 (2025) - 2160p.WEB-DL.H265.10bit.DDP2.0.mkv",
        "timestamp": "2025-04-02T22:39:57.656886",
        "category": "movie",
        "tmdb_id": "1432009",
        "tmdb_url": "https://www.themoviedb.org/movie/1432009",
        "plot": "\"紀錄片首曝電影《哪吒之魔童鬧海》的幕後製作過程，導演餃子和全國四千多名動畫人一起墊腳觸碰創作天花板的故事。\n　　通過紀錄團隊中製作人員的工作瞬間或閒暇趣事，展現中國動畫電影人不斷突破想像力、突破自我、突破極限的頑\"強精神與樂觀態度，及\"人生不設限\"的價值觀。\"\n\n\nThe documentary reveals the behind-the-scenes production process of the film 「Ne Zha 2」, telling the story of director Jiaozi and more than 4,000 animators across the country striving to push the boundaries of creativity. Through moments of work and lighthearted interactions among the production team, the film showcases the relentless spirit, optimism, and boundless imagination of Chinese animation filmmakers as they continuously break through creative limits and personal barriers, embodying the philosophy that 「life has no limits.」"
    },
    {
        "filename": "四度誘惑 Temptation summary II (1991).mp4",
        "absolute_path": "H:\\共用雲端硬碟\\@LiangTsaoEmby_本月更新\\電影\\四度誘惑 Temptation summary II (1991)\\四度誘惑 Temptation summary II (1991).mp4",
        "relative_path": "@LiangTsaoEmby_本月更新\\電影\\四度誘惑 Temptation summary II (1991)\\四度誘惑 Temptation summary II (1991).mp4",
        "timestamp": "2025-04-02T22:44:25.066524",
        "category": "movie",
        "tmdb_id": "436042",
        "tmdb_url": "https://www.themoviedb.org/movie/436042",
        "plot": "在《三度誘惑》誘人的成績下，《四度誘惑》開拍，而男角人選亦不作他選，仍由李中寧出任，扮演戇直CID阿志。在一次放蛇行動中，阿志巧遇徐曼華飾演的阿華，竟對她留下深刻印象，並不惜放她一馬。 與華一起自大陸來港的有小芳，二人均為自己的目標而奮鬥，華一心移民他方，而小芳則希望賺多些錢與大陸男友建立一美滿家庭。華以出賣肉體的積蓄購來一本護照，誰知該國突然發生政變，新政府對過去所發出的護照一概不承認，害得華欲哭無淚；而此時小芳又接獲男友來電錶示要與她...\n\nWhen two prostitutes Wah and Fong find their dreams shattered, they turn to be starred in the sex movies. A second class actress Tracy intentionally exposes her body that brings her lots of movie contract and a wealthy guy. She also seduces her sister's boyfriend and gets him caught. Her despairingly sister, losing all she uses to have, chooses to play in the pornographic movies"
    },
    {
        "filename": "尼克男孩／五分錢男孩 Nickel Boys (2024) - 2160p.WEB-DL.DDP5.1.Atmos.SDR.H265.mkv",
        "absolute_path": "H:\\共用雲端硬碟\\@LiangTsaoEmby_本月更新\\電影\\尼克男孩／五分錢男孩 Nickel Boys (2024)\\尼克男孩／五分錢男孩 Nickel Boys (2024) - 2160p.WEB-DL.DDP5.1.Atmos.SDR.H265.mkv",
        "relative_path": "@LiangTsaoEmby_本月更新\\電影\\尼克男孩／五分錢男孩 Nickel Boys (2024)\\尼克男孩／五分錢男孩 Nickel Boys (2024) - 2160p.WEB-DL.DDP5.1.Atmos.SDR.H265.mkv",
        "timestamp": "2025-04-02T22:44:35.767745",
        "category": "movie",
        "tmdb_id": "1028196",
        "tmdb_url": "https://www.themoviedb.org/movie/1028196",
        "plot": "入圍2025金球獎最佳劇情片獎。描述1960年代兩位非裔男孩被送到佛羅里達州一個充斥虐待的感化院的故事。"
    },
    {
        "filename": "尼克男孩／五分錢男孩 Nickel Boys (2024) - 1080p.web.h264.mp4",
        "absolute_path": "H:\\共用雲端硬碟\\@LiangTsaoEmby_本月更新\\電影\\尼克男孩／五分錢男孩 Nickel Boys (2024)\\尼克男孩／五分錢男孩 Nickel Boys (2024) - 1080p.web.h264.mp4",
        "relative_path": "@LiangTsaoEmby_本月更新\\電影\\尼克男孩／五分錢男孩 Nickel Boys (2024)\\尼克男孩／五分錢男孩 Nickel Boys (2024) - 1080p.web.h264.mp4",
        "timestamp": "2025-04-02T22:44:46.604130",
        "category": "movie",
        "tmdb_id": "1028196",
        "tmdb_url": "https://www.themoviedb.org/movie/1028196",
        "plot": "入圍2025金球獎最佳劇情片獎。描述1960年代兩位非裔男孩被送到佛羅里達州一個充斥虐待的感化院的故事。"
    },
    {
        "filename": "尼克男孩／五分錢男孩 Nickel Boys (2024).mkv",
        "absolute_path": "H:\\共用雲端硬碟\\@LiangTsaoEmby_本月更新\\電影\\尼克男孩／五分錢男孩 Nickel Boys (2024)\\尼克男孩／五分錢男孩 Nickel Boys (2024).mkv",
        "relative_path": "@LiangTsaoEmby_本月更新\\電影\\尼克男孩／五分錢男孩 Nickel Boys (2024)\\尼克男孩／五分錢男孩 Nickel Boys (2024).mkv",
        "timestamp": "2025-04-02T22:44:57.264331",
        "category": "movie",
        "tmdb_id": "1028196",
        "tmdb_url": "https://www.themoviedb.org/movie/1028196",
        "plot": "入圍2025金球獎最佳劇情片獎。描述1960年代兩位非裔男孩被送到佛羅里達州一個充斥虐待的感化院的故事。"
    },
    {
        "filename": "生命清單 The Life List (2025) - 2160p.NF.WEB-DL.DDP5.1.Atmos.HDR.H.265.mkv",
        "absolute_path": "H:\\共用雲端硬碟\\@LiangTsaoEmby_本月更新\\電影\\生命清單 The Life List (2025)\\生命清單 The Life List (2025) - 2160p.NF.WEB-DL.DDP5.1.Atmos.HDR.H.265.mkv",
        "relative_path": "@LiangTsaoEmby_本月更新\\電影\\生命清單 The Life List (2025)\\生命清單 The Life List (2025) - 2160p.NF.WEB-DL.DDP5.1.Atmos.HDR.H.265.mkv",
        "timestamp": "2025-04-02T22:46:10.292905",
        "category": "movie",
        "tmdb_id": "1254786",
        "tmdb_url": "https://www.themoviedb.org/movie/1254786",
        "plot": "年輕女子遵從母親的願望，努力去完成十幾歲時寫下的人生願望清單，過程中不僅挖掘出家族祕密、找到愛情，也重新認識了自己。"
    },
    {
        "filename": "生命清單 The Life List (2025).mkv",
        "absolute_path": "H:\\共用雲端硬碟\\@LiangTsaoEmby_本月更新\\電影\\生命清單 The Life List (2025)\\生命清單 The Life List (2025).mkv",
        "relative_path": "@LiangTsaoEmby_本月更新\\電影\\生命清單 The Life List (2025)\\生命清單 The Life List (2025).mkv",
        "timestamp": "2025-04-02T22:46:20.924747",
        "category": "movie",
        "tmdb_id": "1254786",
        "tmdb_url": "https://www.themoviedb.org/movie/1254786",
        "plot": "年輕女子遵從母親的願望，努力去完成十幾歲時寫下的人生願望清單，過程中不僅挖掘出家族祕密、找到愛情，也重新認識了自己。"
    },
    {
        "filename": "印度先生 Mr.India (1987) - 1080p.BluRay.x265.10bit.DTS.2Audio-QuickIO.mkv",
        "absolute_path": "H:\\共用雲端硬碟\\@LiangTsaoEmby_本月更新\\電影\\印度先生 Mr.India (1987)\\印度先生 Mr.India (1987) - 1080p.BluRay.x265.10bit.DTS.2Audio-QuickIO.mkv",
        "relative_path": "@LiangTsaoEmby_本月更新\\電影\\印度先生 Mr.India (1987)\\印度先生 Mr.India (1987) - 1080p.BluRay.x265.10bit.DTS.2Audio-QuickIO.mkv",
        "timestamp": "2025-04-02T22:46:40.955058",
        "category": "movie",
        "tmdb_id": "41903",
        "tmdb_url": "https://www.themoviedb.org/movie/41903",
        "plot": "艾倫（亞尼·卡普 Anil Kapoor 飾）的父親，瓦爾馬博士，是一位傑出的科學家，他憑藉光學原理發明瞭一款神奇的手鐲，能夠讓人隱形。然而，穆甘博得知了這個發明，並派人前來索取，但瓦爾馬博士拒絕交出。於是，穆甘博野心勃勃，為了謀取利益，不惜殺害了瓦爾馬博士。穆甘博企圖稱霸印度，他在軒市進行軍火交易，建立了導彈基地，威脅著印度各個重要設施。艾倫長大後，收養了七八個孩童，並租出空房，其中一位名叫西瑪的姑娘成為了他們的承租人，與孩子們逐漸打成一片。\n　　某一天，穆甘博的手下在街上遇到了瓦爾馬博士的助手辛哈教授，教授成功逃脫後，告知了艾倫手鐲的下落。艾倫得到手鐲後，變成了隱形人，並自稱為「印度先生」，開始行動懲惡揚善。穆甘博得知此事後，綁架了艾倫、西瑪和孩子們，企圖引出「印度先生」。在匪巢裡，艾倫利用手鐲的力量嚴懲了眾匪徒，而穆甘博卻瘋狂到要炸毀整個印度，被艾倫制服。\n\n\nA poor but big-hearted man takes orphans into his home. After discovering his scientist father's invisibility device, he rises to the occasion and fights to save his children and all of India from the clutches of a megalomaniac."
    },
    {
        "filename": "西游降魔篇之快活城 (2025).mkv",
        "absolute_path": "H:\\共用雲端硬碟\\@LiangTsaoEmby_本月更新\\電影\\西遊降魔篇之快活城 (2025)\\西游降魔篇之快活城 (2025).mkv",
        "relative_path": "@LiangTsaoEmby_本月更新\\電影\\西遊降魔篇之快活城 (2025)\\西游降魔篇之快活城 (2025).mkv",
        "timestamp": "2025-04-02T22:47:00.980633",
        "category": "movie",
        "tmdb_id": "1452244",
        "tmdb_url": "https://www.themoviedb.org/movie/1452244",
        "plot": "「半妖」驅魔人常平安，為去除自身妖性前往快活城尋丹，受殷夫子蠱惑，錯殺了善良且深愛自己的女妖小紅癲，體內邪惡的妖魔元靈被喚醒，妖魔肆虐人間。最終，變成人的他選擇吃下妖丹變成妖，攜手眾驅魔人收服妖魔。"
    },
    {
        "filename": "你好陌生人 Hello Stranger (2010).mp4",
        "absolute_path": "H:\\共用雲端硬碟\\@LiangTsaoEmby_本月更新\\電影\\你好陌生人 Hello Stranger (2010)\\你好陌生人 Hello Stranger (2010).mp4",
        "relative_path": "@LiangTsaoEmby_本月更新\\電影\\你好陌生人 Hello Stranger (2010)\\你好陌生人 Hello Stranger (2010).mp4",
        "timestamp": "2025-04-02T22:47:10.997741",
        "category": "movie",
        "tmdb_id": "50938",
        "tmdb_url": "https://www.themoviedb.org/movie/50938",
        "plot": "泰國男生Dak（辰塔維·塔納西維 Chantawit Thanasewee 飾）因拒絕與女友結婚而被拋棄。喝得爛醉後隔天獨自踏上原先和女友預訂的韓國旅程。宿醉語言又不通的Dak只能向，只能向一名泰國女生May求助（努娜能提妲莎彭 Noona Nuength ida Sophon 飾）。May有一位大男子主義，對她管得徹頭徹尾的男友金哥，這一次是背著男友偷跑來韓國參加好友的婚禮。因為漏接金哥的電話導致兩人大吵一頓最後分手。Dak一直留在她身邊安慰，兩人一起去酒吧，一起去參觀韓劇的拍攝地點。雖然彼此都不知道對方的名字，但兩人慢慢從冤家慢慢聊成知己，就在情愫漸生之時，Dak的女友突然出現。Dak是會選擇重新回到女朋友的身邊，還是這一對熟悉的陌生人最終會終成眷屬。\n\nTwo strangers meet in South Korea, each on a vacation.  When he misses his tour bus, he asks a woman if he can hang out with her for a few days.  They have fun together, but never tell each other their names.  So when the trip is over they don't know how to contact each other."
    },
    {
        "filename": "印度刺客：薩達爾．辛格 Sardar Udham (2021) - 1080p.AMZN.WEB-DL.DDP5.1.Atmos.H264-ParkHD.mkv",
        "absolute_path": "H:\\共用雲端硬碟\\@LiangTsaoEmby_本月更新\\電影\\印度刺客：薩達爾．辛格 Sardar Udham (2021)\\印度刺客：薩達爾．辛格 Sardar Udham (2021) - 1080p.AMZN.WEB-DL.DDP5.1.Atmos.H264-ParkHD.mkv",
        "relative_path": "@LiangTsaoEmby_本月更新\\電影\\印度刺客：薩達爾．辛格 Sardar Udham (2021)\\印度刺客：薩達爾．辛格 Sardar Udham (2021) - 1080p.AMZN.WEB-DL.DDP5.1.Atmos.H264-ParkHD.mkv",
        "timestamp": "2025-04-02T22:47:21.010311",
        "category": "movie",
        "tmdb_id": "598826",
        "tmdb_url": "https://www.themoviedb.org/movie/598826",
        "plot": "年輕的薩達爾·辛格深受札連瓦拉園大屠殺創傷。他逃進阿富汗的深山裡，在1933年到1934年期間到達倫敦。辛格在那裡過了最關鍵的六年，重燃革命。在1940年3月13日，薩達爾·辛格帶著21年來從未治癒的創傷，暗殺了麥可·奧德懷爾，就是在1919年4月主導旁遮普邦事件的那個人。"
    },
    {
        "filename": "你的國，我的家／唯一的家園 No Other Land (2024).mp4",
        "absolute_path": "H:\\共用雲端硬碟\\@LiangTsaoEmby_本月更新\\電影\\你的國，我的家／唯一的家園 No Other Land (2024)\\你的國，我的家／唯一的家園 No Other Land (2024).mp4",
        "relative_path": "@LiangTsaoEmby_本月更新\\電影\\你的國，我的家／唯一的家園 No Other Land (2024)\\你的國，我的家／唯一的家園 No Other Land (2024).mp4",
        "timestamp": "2025-04-02T22:47:31.027684",
        "category": "movie",
        "tmdb_id": "1232493",
        "tmdb_url": "https://www.themoviedb.org/movie/1232493",
        "plot": "位於巴勒斯坦西岸的馬薩費爾亞塔，自八〇年代起被以色列政府劃為軍用「開火區」，土地上的巴勒斯坦居民被裁定為非法居住，展開面對軍方恐嚇迫遷、強拆騷擾的漫長抗爭。年輕的巴勒斯坦居民巴索，追隨父親成為運動者及公民記者，他與以色列記者尤法成為朋友，致力以鏡頭作為反抗，直擊以色列軍隊對待巴勒斯坦平民的暴力日常，呈現抗爭中的脆弱與韌性。但隨著軍隊暴力升級，絕望、無力與憂鬱如煙延綿，兩人也不禁對紀錄這件事產生懷疑。"
    },
    {
        "filename": "我依然在此／我仍在此 I'm Still Here (2024) - 720p.SCREENER.WEB-DL.x264-NGP.mkv",
        "absolute_path": "H:\\共用雲端硬碟\\@LiangTsaoEmby_本月更新\\電影\\我依然在此／我仍在此 I'm Still Here (2024)\\我依然在此／我仍在此 I'm Still Here (2024) - 720p.SCREENER.WEB-DL.x264-NGP.mkv",
        "relative_path": "@LiangTsaoEmby_本月更新\\電影\\我依然在此／我仍在此 I'm Still Here (2024)\\我依然在此／我仍在此 I'm Still Here (2024) - 720p.SCREENER.WEB-DL.x264-NGP.mkv",
        "timestamp": "2025-04-02T22:56:31.649261",
        "category": "movie",
        "tmdb_id": "1000837",
        "tmdb_url": "https://www.themoviedb.org/movie/1000837",
        "plot": "1970年的里約熱內盧，沙灘上到處是嬉鬧人群，魯本斯與尤妮絲一家七口就住在海濱街區，與朋友聚會、歡笑暢談、拍照留念是他們的日常；但同時，不滿獨裁政府的反對聲浪四起，也讓白色恐怖逐漸蔓延每個角落。一日，意外的訪客打破平靜，魯本斯遭軍方強行帶走，自此下落不明。悲痛的尤妮絲被迫挺身而出，找尋丈夫失蹤的真相，並獨自撐起這個家，以堅定的心持續帶給孩子們完整的愛與希望。"
    },
    {
        "filename": "沙漠妖姬 The Adventures of Priscilla, Queen of the Desert (1994) - 4K.mkv",
        "absolute_path": "H:\\共用雲端硬碟\\@LiangTsaoEmby_本月更新\\電影\\沙漠妖姬 The Adventures of Priscilla, Queen of the Desert (1994)\\沙漠妖姬 The Adventures of Priscilla, Queen of the Desert (1994) - 4K.mkv",
        "relative_path": "@LiangTsaoEmby_本月更新\\電影\\沙漠妖姬 The Adventures of Priscilla, Queen of the Desert (1994)\\沙漠妖姬 The Adventures of Priscilla, Queen of the Desert (1994) - 4K.mkv",
        "timestamp": "2025-04-02T22:56:41.672776",
        "category": "movie",
        "tmdb_id": "2759",
        "tmdb_url": "https://www.themoviedb.org/movie/2759",
        "plot": "異裝癖表演者班麗娜（Terence Stamp 飾）、米芝（Hugo Weaving 飾）因一位好友去世而再度聚首，米芝得到澳洲中部城市的表演機會邀請班麗娜同往，同行費莉茜（Guy Pearce 飾）為圓“沙漠女王”之夢要求搭夥，並借來了經改裝的大巴作為代步工具。三人風風火火的踏上旅程，上了年紀的班麗娜于路對往事諱莫如深，與年輕躁動的費莉茜生出不少瑣碎口角，米芝則不時陷入對自己那場婚姻的回憶。他們在沿途經過的小鎮大秀妖冶，得到了不少驚愕的目光，當然也有贊許。因為一次拋錨，對班麗娜昔日表演難以忘懷的修理工老巴得以加入他們的旅程。眾人終於抵達目的地，雖然觀眾不甚熱情，但米芝終於見到了兒子，而班麗娜決定和老巴在一起……\n　　本片獲1995年奧斯卡最佳服裝設計獎等多項褒獎。\n\n\nTwo drag queens and a transgender woman contract to perform a drag show at a resort in Alice Springs, a town in the remote Australian desert. As they head west from Sydney aboard their lavender bus, Priscilla, the three friends come to the forefront of a comedy of errors, encountering a number of strange characters, as well as incidents of homophobia, whilst widening comfort zones and exploring new horizons."
    },
    {
        "filename": "你的婚禮 My Love (2021) - 2160p.WEB-DL.60Fps.H265.10bit.DTS5.1-UBWEB.mkv",
        "absolute_path": "H:\\共用雲端硬碟\\@LiangTsaoEmby_本月更新\\電影\\你的婚禮 My Love (2021)\\你的婚禮 My Love (2021) - 2160p.WEB-DL.60Fps.H265.10bit.DTS5.1-UBWEB.mkv",
        "relative_path": "@LiangTsaoEmby_本月更新\\電影\\你的婚禮 My Love (2021)\\你的婚禮 My Love (2021) - 2160p.WEB-DL.60Fps.H265.10bit.DTS5.1-UBWEB.mkv",
        "timestamp": "2025-04-02T22:56:51.704134",
        "category": "movie",
        "tmdb_id": "723640",
        "tmdb_url": "https://www.themoviedb.org/movie/723640",
        "plot": "高中時期，功課不好、整天打架鬧事的體育生周瀟齊（許光漢 飾）對轉學生尤詠慈（章若楠 飾）一見鍾情；年少懵懂的週瀟齊純純愛戀著尤詠慈，他默默守護，卻換來尤詠慈的不告而別。此後的人生，一段長達15年的愛情故事即將展開……"
    },
    {
        "filename": "辛辛監獄劇團／監獄劇院 Sing Sing (2023).mp4",
        "absolute_path": "H:\\共用雲端硬碟\\@LiangTsaoEmby_本月更新\\電影\\辛辛監獄劇團／監獄劇院 Sing Sing (2023)\\辛辛監獄劇團／監獄劇院 Sing Sing (2023).mp4",
        "relative_path": "@LiangTsaoEmby_本月更新\\電影\\辛辛監獄劇團／監獄劇院 Sing Sing (2023)\\辛辛監獄劇團／監獄劇院 Sing Sing (2023).mp4",
        "timestamp": "2025-04-02T22:57:01.722725",
        "category": "movie",
        "tmdb_id": "1155828",
        "tmdb_url": "https://www.themoviedb.org/movie/1155828",
        "plot": "因未犯下的罪行而被關押在監獄的神聖G，與其他被監禁的人一起在劇團中表演，找到了人生意義。"
    },
    {
        "filename": "里斯本的故事 Lisbon Story (1994) - 1080p.BluRay.x265.10bit.DTS-SONYHD.mkv",
        "absolute_path": "H:\\共用雲端硬碟\\@LiangTsaoEmby_本月更新\\電影\\里斯本的故事 Lisbon Story (1994)\\里斯本的故事 Lisbon Story (1994) - 1080p.BluRay.x265.10bit.DTS-SONYHD.mkv",
        "relative_path": "@LiangTsaoEmby_本月更新\\電影\\里斯本的故事 Lisbon Story (1994)\\里斯本的故事 Lisbon Story (1994) - 1080p.BluRay.x265.10bit.DTS-SONYHD.mkv",
        "timestamp": "2025-04-02T22:57:11.740438",
        "category": "movie",
        "tmdb_id": "390",
        "tmdb_url": "https://www.themoviedb.org/movie/390",
        "plot": "一張寫著求救字眼的風景明信片，讓電影錄音師菲利普(魯迪格福格勒飾)風塵僕僕趕往葡萄牙里斯本，途中他的車壞了，最後千辛萬苦抵達時卻只找到了沒有完成音效的電影膠卷，他的導演朋友菲德利希(派屈克波查飾)消失了，於是菲利普留在里斯本，發掘被人們忽略的城市聲音，並結識了一群樂團好友，他甚至迷戀上歌聲如黃鶯出谷的女歌手泰瑞莎…"
    },
    {
        "filename": "來自誰的啟示 계시록 Revelations (2025).mkv",
        "absolute_path": "H:\\共用雲端硬碟\\@LiangTsaoEmby_本月更新\\電影\\來自誰的啟示 계시록 Revelations (2025)\\來自誰的啟示 계시록 Revelations (2025).mkv",
        "relative_path": "@LiangTsaoEmby_本月更新\\電影\\來自誰的啟示 계시록 Revelations (2025)\\來自誰的啟示 계시록 Revelations (2025).mkv",
        "timestamp": "2025-04-02T22:57:21.763682",
        "category": "movie",
        "tmdb_id": "1210938",
        "tmdb_url": "https://www.themoviedb.org/movie/1210938",
        "plot": "相信神諭的牧師與深受幻覺所苦的刑警都在追查同一樁失蹤案，他倆各自的心魔也在過程中浮現。"
    },
    {
        "filename": "刺激驚爆點／非常嫌疑犯 The Usual Suspects (1995).mkv",
        "absolute_path": "H:\\共用雲端硬碟\\@LiangTsaoEmby_本月更新\\電影\\刺激驚爆點／非常嫌疑犯 The Usual Suspects (1995)\\刺激驚爆點／非常嫌疑犯 The Usual Suspects (1995).mkv",
        "relative_path": "@LiangTsaoEmby_本月更新\\電影\\刺激驚爆點／非常嫌疑犯 The Usual Suspects (1995)\\刺激驚爆點／非常嫌疑犯 The Usual Suspects (1995).mkv",
        "timestamp": "2025-04-02T22:57:31.776134",
        "category": "movie",
        "tmdb_id": "629",
        "tmdb_url": "https://www.themoviedb.org/movie/629",
        "plot": "美國加州的聖佩雷羅港一艘貨輪爆炸，死亡27人，9000萬美元失蹤。事故發生以後，聯邦調查局探員白基奇在醫院等待昏迷不醒的倖存者；海關特派員大衛（查茲•帕明特裡 飾）則對另外一名拿到特赦令的倖存者金特（凱文•史派西 飾）進行了審問。金特供認，在事故中喪生的基頓（加布裡埃爾•伯恩 飾）、法特（本尼西奧•德托羅 飾）、麥曼諾（斯蒂芬•鮑爾文 飾）和杜學尼（凱文•波拉克 飾），以及他本人，六個月前被警察局作為卡車搶劫案的疑犯帶到警局過了一夜，五人因此結成了一個犯罪團伙，狼狽為奸……"
    },
    {
        "filename": "妻人太甚／我妻子的一切 내 아내의 모든 것 All About My Wife (2012) - BluRay.1080p.x264.DTS-CMCT.mkv",
        "absolute_path": "H:\\共用雲端硬碟\\@LiangTsaoEmby_本月更新\\電影\\妻人太甚／我妻子的一切 내 아내의 모든 것 All About My Wife (2012)\\妻人太甚／我妻子的一切 내 아내의 모든 것 All About My Wife (2012) - BluRay.1080p.x264.DTS-CMCT.mkv",
        "relative_path": "@LiangTsaoEmby_本月更新\\電影\\妻人太甚／我妻子的一切 내 아내의 모든 것 All About My Wife (2012)\\妻人太甚／我妻子的一切 내 아내의 모든 것 All About My Wife (2012) - BluRay.1080p.x264.DTS-CMCT.mkv",
        "timestamp": "2025-04-02T22:57:41.788297",
        "category": "movie",
        "tmdb_id": "116488",
        "tmdb_url": "https://www.themoviedb.org/movie/116488",
        "plot": "出門是貴婦、在家是巧婦、床上是蕩婦 美麗出眾又擁有完美廚藝的正茵，在眾人眼中是宛如天使般的美嬌娘，但在丈夫斗賢眼中，卻是最恐怖的野蠻人妻。她刁蠻任性，在公眾場合更時常口不擇言，丈夫忍辱偷生卻不敢提­出離婚，終於在崩潰邊緣覓得一線生機：重金禮聘知名花花公子來誘惑正茵，好讓這夢魘般的惡妻主動提出離婚。 愛情文藝片還能玩出什麼花樣？本片再度證明韓國電影擁有卓越的編劇與商業操作能力。網羅韓國首席女星林秀晶與李善均、柳昇龍主演。超級有梗的情節以及令人忍不住想拚命劃重­點的絕妙對白，加上片中時而大秀曼妙美腿，時而如機關槍喋喋不休的小惡魔林秀晶，告訴你什麼才叫正港的犀利人妻！ 導演閔奎東是韓國票房常勝軍：「我想藉由全新的輕喜劇方式來描繪這些時刻，從中發掘出愛情的另一種意義。」"
    },
    {
        "filename": "雨中的慾情／雨中的情欲 Lust in the Rain (2024).mp4",
        "absolute_path": "H:\\共用雲端硬碟\\@LiangTsaoEmby_本月更新\\電影\\雨中的慾情／雨中的情欲 Lust in the Rain (2024)\\雨中的慾情／雨中的情欲 Lust in the Rain (2024).mp4",
        "relative_path": "@LiangTsaoEmby_本月更新\\電影\\雨中的慾情／雨中的情欲 Lust in the Rain (2024)\\雨中的慾情／雨中的情欲 Lust in the Rain (2024).mp4",
        "timestamp": "2025-04-02T22:57:51.805693",
        "category": "movie",
        "tmdb_id": "1283793",
        "tmdb_url": "https://www.themoviedb.org/movie/1283793",
        "plot": "時代未知，地點不明。潦倒漫畫家義男窩居北町小鎮，對寡婦福子一見鍾情，卻被小說家伊守捷足先登。有生意頭腦的伊守學起富饒南町創辦商場雜誌，義男負責招商，八字還沒一撇，業務就捲款潛逃。為躲避債主，三人被迫展開同居生活。福子與伊守夜夜性愛，義男只能在暗處窺伺，性慾、愛慾、生之慾交錯的異次元在眼前無限膨脹，一切變得超乎預期。"
    },
    {
        "filename": "非常男人／不同的男人 A Different Man (2024).mkv",
        "absolute_path": "H:\\共用雲端硬碟\\@LiangTsaoEmby_本月更新\\電影\\非常男人／不同的男人 A Different Man (2024)\\非常男人／不同的男人 A Different Man (2024).mkv",
        "relative_path": "@LiangTsaoEmby_本月更新\\電影\\非常男人／不同的男人 A Different Man (2024)\\非常男人／不同的男人 A Different Man (2024).mkv",
        "timestamp": "2025-04-02T22:58:01.823588",
        "category": "movie",
        "tmdb_id": "989662",
        "tmdb_url": "https://www.themoviedb.org/movie/989662",
        "plot": "臉上生了巨瘤的愛德華懷抱著演員夢，卻因外貌感到自卑，即使愛慕美麗的鄰居英格麗，也只敢暗藏在心內。直到一場實驗手術讓他脫胎換骨獲得俊俏臉龐，愛德華決定改名換姓展開新生。沒想到一齣以昔日自己為主角的戲劇正在排練，編導竟是英格麗。他戴上面具爭取這場非他莫屬的演出，好不容易迎來女神一親芳澤，登臺秀卻殺出程咬金，原以為的夢想成真，竟一夕間成了噩夢。"
    },
    {
        "filename": "柏靈頓：熊熊去秘魯 (2024)／帕丁頓熊3：秘魯大冒險 Paddington in Peru (2024) - 4K.mkv",
        "absolute_path": "H:\\共用雲端硬碟\\@LiangTsaoEmby_本月更新\\電影\\柏靈頓：熊熊去秘魯 (2024)／帕丁頓熊3：秘魯大冒險 Paddington in Peru (2024)\\柏靈頓：熊熊去秘魯 (2024)／帕丁頓熊3：秘魯大冒險 Paddington in Peru (2024) - 4K.mkv",
        "relative_path": "@LiangTsaoEmby_本月更新\\電影\\柏靈頓：熊熊去秘魯 (2024)／帕丁頓熊3：秘魯大冒險 Paddington in Peru (2024)\\柏靈頓：熊熊去秘魯 (2024)／帕丁頓熊3：秘魯大冒險 Paddington in Peru (2024) - 4K.mkv",
        "timestamp": "2025-04-02T22:58:11.844345",
        "category": "movie",
        "tmdb_id": "516729",
        "tmdb_url": "https://www.themoviedb.org/movie/516729",
        "plot": "柏靈頓熊熊來到祕魯的退休熊之家，拜訪他親愛的露西姑姑，他們與布朗一家又再次被捲入一起神秘事件，前往亞馬遜雨林和秘魯的深山之中，展開一場刺激的冒險之旅。"
    },
    {
        "filename": "拿針的女孩 The Girl with the Needle (2024) - 4K.mkv",
        "absolute_path": "H:\\共用雲端硬碟\\@LiangTsaoEmby_本月更新\\電影\\拿針的女孩 The Girl with the Needle (2024)\\拿針的女孩 The Girl with the Needle (2024) - 4K.mkv",
        "relative_path": "@LiangTsaoEmby_本月更新\\電影\\拿針的女孩 The Girl with the Needle (2024)\\拿針的女孩 The Girl with the Needle (2024) - 4K.mkv",
        "timestamp": "2025-04-02T22:58:21.862547",
        "category": "movie",
        "tmdb_id": "1232827",
        "tmdb_url": "https://www.themoviedb.org/movie/1232827",
        "plot": "《拿針的女孩》是一部 2024 年歷史心理恐怖電影，由馬格努斯·馮·霍恩執導，劇本由馮·霍恩和萊恩·蘭格貝克編劇。本片以1919 年為背景，維克·卡門·索恩(Vic Carmen Sonne) 飾演一名年輕女子，她開始在一家為弱勢母親服務的秘密收養機構擔任奶媽，但她對經營該機構的女性產生了懷疑。"
    },
    {
        "filename": "泰勒派瑞之口是心非／表裡不一 Tyler Perry's Duplicity (2025).mkv",
        "absolute_path": "H:\\共用雲端硬碟\\@LiangTsaoEmby_本月更新\\電影\\泰勒派瑞之口是心非／表裡不一 Tyler Perry's Duplicity (2025)\\泰勒派瑞之口是心非／表裡不一 Tyler Perry's Duplicity (2025).mkv",
        "relative_path": "@LiangTsaoEmby_本月更新\\電影\\泰勒派瑞之口是心非／表裡不一 Tyler Perry's Duplicity (2025)\\泰勒派瑞之口是心非／表裡不一 Tyler Perry's Duplicity (2025).mkv",
        "timestamp": "2025-04-02T22:58:31.881658",
        "category": "movie",
        "tmdb_id": "1145725",
        "tmdb_url": "https://www.themoviedb.org/movie/1145725",
        "plot": "精明能幹的瑪莉律師接下最私人的案件，她必須找出閨密費拉的丈夫慘遭殺害的真相。曾任警員的私家偵探男友協助瑪莉調查事發經過，卻也讓她步步走向充滿欺騙與背叛的詭譎謎團。"
    },
    {
        "filename": "寄生獸 Parasyte：Part 1 (2014) - 4K.mkv",
        "absolute_path": "H:\\共用雲端硬碟\\@LiangTsaoEmby_本月更新\\電影\\寄生獸 Parasyte：Part 1 (2014)\\寄生獸 Parasyte：Part 1 (2014) - 4K.mkv",
        "relative_path": "@LiangTsaoEmby_本月更新\\電影\\寄生獸 Parasyte：Part 1 (2014)\\寄生獸 Parasyte：Part 1 (2014) - 4K.mkv",
        "timestamp": "2025-04-02T22:58:41.898673",
        "category": "movie",
        "tmdb_id": "282069",
        "tmdb_url": "https://www.themoviedb.org/movie/282069",
        "plot": "超高人氣漫畫改編，橋本愛主演。某天於地球上空出現許多孢子，其中誕生的幼蟲侵入身體後，以寄生於腦部為目標，寄生完成後與腦部細胞同化。他能任意變形，其食物是與寄生體相同的物種─人類。"
    },
    {
        "filename": "偷香 Stealing Beauty (1996) - BluRay.1080p.DTS-HD.MA.5.1.x265.10bit-DreamHD.mkv",
        "absolute_path": "H:\\共用雲端硬碟\\@LiangTsaoEmby_本月更新\\電影\\偷香 Stealing Beauty (1996)\\偷香 Stealing Beauty (1996) - BluRay.1080p.DTS-HD.MA.5.1.x265.10bit-DreamHD.mkv",
        "relative_path": "@LiangTsaoEmby_本月更新\\電影\\偷香 Stealing Beauty (1996)\\偷香 Stealing Beauty (1996) - BluRay.1080p.DTS-HD.MA.5.1.x265.10bit-DreamHD.mkv",
        "timestamp": "2025-04-02T22:58:51.917177",
        "category": "movie",
        "tmdb_id": "14553",
        "tmdb_url": "https://www.themoviedb.org/movie/14553",
        "plot": "19歲的美國少女露西（麗芙泰勒飾），在母親死後決定前往義大利的一個小鎮尋找母親的昔日故友，並在當地擔任一名雕塑家的模特兒。但是，仍為處女的露西無法靜心領會這一片鄉間的寧靜，她遲疑良久才敢再見四年前吻過的男孩，並體會到她母親日記中那一段莫名的情結。  露西這樣一名美國少女的出現，為群居於當地的藝術家及文人帶來一股新生氣，而且她那純潔無暇之美，也挑起了這群人的情慾面，使得她尚未解開母親一生的謎團前，已使得眾人的生活秩序大亂。  最後露西終於找到自己的生父，並與一名男孩展開甜蜜的戀情，也體會了自由奔放的母親所留下的一切。"
    },
    {
        "filename": "寄生獸2：完結篇 Parasyte：Part 2 (2015).mkv",
        "absolute_path": "H:\\共用雲端硬碟\\@LiangTsaoEmby_本月更新\\電影\\寄生獸2：完結篇 Parasyte：Part 2 (2015)\\寄生獸2：完結篇 Parasyte：Part 2 (2015).mkv",
        "relative_path": "@LiangTsaoEmby_本月更新\\電影\\寄生獸2：完結篇 Parasyte：Part 2 (2015)\\寄生獸2：完結篇 Parasyte：Part 2 (2015).mkv",
        "timestamp": "2025-04-02T22:59:01.930941",
        "category": "movie",
        "tmdb_id": "282070",
        "tmdb_url": "https://www.themoviedb.org/movie/282070",
        "plot": "最強物種現身 大戰一觸即發！全人類V.S寄生生物 終極之戰即將引爆。我能夠守護我所愛的人嗎？"
    },
    {
        "filename": "從不，很少，有時，總是 Never Rarely Sometimes Always (2020).mp4",
        "absolute_path": "H:\\共用雲端硬碟\\@LiangTsaoEmby_本月更新\\電影\\從不，很少，有時，總是 Never Rarely Sometimes Always (2020)\\從不，很少，有時，總是 Never Rarely Sometimes Always (2020).mp4",
        "relative_path": "@LiangTsaoEmby_本月更新\\電影\\從不，很少，有時，總是 Never Rarely Sometimes Always (2020)\\從不，很少，有時，總是 Never Rarely Sometimes Always (2020).mp4",
        "timestamp": "2025-04-02T22:59:11.939684",
        "category": "movie",
        "tmdb_id": "595671",
        "tmdb_url": "https://www.themoviedb.org/movie/595671",
        "plot": "賓夕法尼亞州兩位互為表親的少女意外懷孕後，踏上了前往紐約墮胎的旅程。  影片於2020年1月24日在日舞影展全球首映，之後入選第70屆柏林影展金熊獎主競賽單元，最終獲得評審團大獎銀熊獎."
    },
    {
        "filename": "異種 Species (1995) - BluRay.mkv",
        "absolute_path": "H:\\共用雲端硬碟\\@LiangTsaoEmby_本月更新\\電影\\異種 Species (1995)\\異種 Species (1995) - BluRay.mkv",
        "relative_path": "@LiangTsaoEmby_本月更新\\電影\\異種 Species (1995)\\異種 Species (1995) - BluRay.mkv",
        "timestamp": "2025-04-02T22:59:22.183045",
        "category": "movie",
        "tmdb_id": "9348",
        "tmdb_url": "https://www.themoviedb.org/movie/9348",
        "plot": "人類長久以來的夢想之一，是証明自己並不是宇宙中唯一生物。為了這答案人類不斷地發出訊號，其中包括人類的DNA結構。  幾年前有了迴音科學家將之解讀，一種是對人類有益的能源另一種則是加上外星生物基因。為了看結果，實驗人員將它培育出成半人半外星生物的「賽兒」（Natasha Henstridge 飾）。當科學人員欲將她殺掉時，她逃了出來，政府秘密組成狙殺小組，以防她繁殖導致毀滅人類。  然「賽兒」成長速度極快又是金髮高挑美人，一般人很難不動心也因而有數名男性死於她手中，為了順利繁衍後代，賽兒設計了一場假車禍，讓世人以為她已身亡。雖然組員中仍有人不相信她已死但行動暫時停擺。  賽兒趁眾人鬆懈時和其中一名組員「完成交配」眾人警覺一路追至下水道殺了她及剛出生的小孩，但事情尚未落幕，異種仍然存在。"
    },
    {
        "filename": "荷蘭鎮 Holland (2025) - 2160p.AMZN.WEB-DL.DDP5.1.Atmos.DV.HDR.H.265.mkv",
        "absolute_path": "H:\\共用雲端硬碟\\@LiangTsaoEmby_本月更新\\電影\\荷蘭鎮 Holland (2025)\\荷蘭鎮 Holland (2025) - 2160p.AMZN.WEB-DL.DDP5.1.Atmos.DV.HDR.H.265.mkv",
        "relative_path": "@LiangTsaoEmby_本月更新\\電影\\荷蘭鎮 Holland (2025)\\荷蘭鎮 Holland (2025) - 2160p.AMZN.WEB-DL.DDP5.1.Atmos.DV.HDR.H.265.mkv",
        "timestamp": "2025-04-02T22:59:32.198078",
        "category": "movie",
        "tmdb_id": "257094",
        "tmdb_url": "https://www.themoviedb.org/movie/257094",
        "plot": "在這部劇情難料的驚悚片中，妮可基嫚飾演細心敏銳兼顧家庭與工作的學校老師，南希范德格魯特。南希和她廣受鄰里仰賴的丈夫與兒子一家三口在盛產鬱金香的密西根州荷蘭鎮過著人人稱羨的完美生活。不料事情有了意外的發展，南希和同事好友為了釐清不尋常之處，意外發現小鎮不如表面單純。"
    },
    {
        "filename": "荷蘭鎮 Holland (2025).mkv",
        "absolute_path": "H:\\共用雲端硬碟\\@LiangTsaoEmby_本月更新\\電影\\荷蘭鎮 Holland (2025)\\荷蘭鎮 Holland (2025).mkv",
        "relative_path": "@LiangTsaoEmby_本月更新\\電影\\荷蘭鎮 Holland (2025)\\荷蘭鎮 Holland (2025).mkv",
        "timestamp": "2025-04-02T22:59:42.214975",
        "category": "movie",
        "tmdb_id": "257094",
        "tmdb_url": "https://www.themoviedb.org/movie/257094",
        "plot": "在這部劇情難料的驚悚片中，妮可基嫚飾演細心敏銳兼顧家庭與工作的學校老師，南希范德格魯特。南希和她廣受鄰里仰賴的丈夫與兒子一家三口在盛產鬱金香的密西根州荷蘭鎮過著人人稱羨的完美生活。不料事情有了意外的發展，南希和同事好友為了釐清不尋常之處，意外發現小鎮不如表面單純。"
    },
    {
        "filename": "焚城 Cesium Fallout (2024) - 2160p.EDR.WEB-DL.H265.DDP5.1.mkv",
        "absolute_path": "H:\\共用雲端硬碟\\@LiangTsaoEmby_本月更新\\電影\\焚城 Cesium Fallout (2024)\\焚城 Cesium Fallout (2024) - 2160p.EDR.WEB-DL.H265.DDP5.1.mkv",
        "relative_path": "@LiangTsaoEmby_本月更新\\電影\\焚城 Cesium Fallout (2024)\\焚城 Cesium Fallout (2024) - 2160p.EDR.WEB-DL.H265.DDP5.1.mkv",
        "timestamp": "2025-04-02T22:59:52.238747",
        "category": "movie",
        "tmdb_id": "1305642",
        "tmdb_url": "https://www.themoviedb.org/movie/1305642",
        "plot": "香港史上首部天價輻射災難鉅製！一場意外引發輻射洩漏，全港命運危在旦夕。為應付這場毀滅性災難，專家范偉立（劉德華 飾）加入由署理行政長官Cecilia（莫文蔚 飾）主持的緊急危機應變小組。700萬人家園隨時毀於一旦，消防隊臨危受命深入輻射區，拚死阻止輻射擴散全港。面對前所未見的末日浩劫，香港會否一夜滅城？"
    },
    {
        "filename": "焚城 Cesium Fallout (2024) - 4K.mkv",
        "absolute_path": "H:\\共用雲端硬碟\\@LiangTsaoEmby_本月更新\\電影\\焚城 Cesium Fallout (2024)\\焚城 Cesium Fallout (2024) - 4K.mkv",
        "relative_path": "@LiangTsaoEmby_本月更新\\電影\\焚城 Cesium Fallout (2024)\\焚城 Cesium Fallout (2024) - 4K.mkv",
        "timestamp": "2025-04-02T23:00:02.252966",
        "category": "movie",
        "tmdb_id": "1305642",
        "tmdb_url": "https://www.themoviedb.org/movie/1305642",
        "plot": "香港史上首部天價輻射災難鉅製！一場意外引發輻射洩漏，全港命運危在旦夕。為應付這場毀滅性災難，專家范偉立（劉德華 飾）加入由署理行政長官Cecilia（莫文蔚 飾）主持的緊急危機應變小組。700萬人家園隨時毀於一旦，消防隊臨危受命深入輻射區，拚死阻止輻射擴散全港。面對前所未見的末日浩劫，香港會否一夜滅城？"
    },
    {
        "filename": "愛樂唯她：紐約愛樂首位女團員 The Only Girl in the Orchestra (2024).mp4",
        "absolute_path": "H:\\共用雲端硬碟\\@LiangTsaoEmby_本月更新\\電影\\愛樂唯她：紐約愛樂首位女團員 The Only Girl in the Orchestra (2024)\\愛樂唯她：紐約愛樂首位女團員 The Only Girl in the Orchestra (2024).mp4",
        "relative_path": "@LiangTsaoEmby_本月更新\\電影\\愛樂唯她：紐約愛樂首位女團員 The Only Girl in the Orchestra (2024)\\愛樂唯她：紐約愛樂首位女團員 The Only Girl in the Orchestra (2024).mp4",
        "timestamp": "2025-04-02T23:00:12.272605",
        "category": "movie",
        "tmdb_id": "1195310",
        "tmdb_url": "https://www.themoviedb.org/movie/1195310",
        "plot": "這部紀錄短片向低音提琴家奧林奧布萊恩致敬，她曾開創先河，成為紐約愛樂聘任的第一位女性正式團員。"
    },
    {
        "filename": "監視與報告／我要當員警 Observe and Report (2009).mkv",
        "absolute_path": "H:\\共用雲端硬碟\\@LiangTsaoEmby_本月更新\\電影\\監視與報告／我要當員警 Observe and Report (2009)\\監視與報告／我要當員警 Observe and Report (2009).mkv",
        "relative_path": "@LiangTsaoEmby_本月更新\\電影\\監視與報告／我要當員警 Observe and Report (2009)\\監視與報告／我要當員警 Observe and Report (2009).mkv",
        "timestamp": "2025-04-02T23:00:22.288345",
        "category": "movie",
        "tmdb_id": "16991",
        "tmdb_url": "https://www.themoviedb.org/movie/16991",
        "plot": "作為商場的保安主管，羅尼（塞斯·羅根 Seth Rogen 飾）對自己的職業很不滿意。在他的幻想裡，他應該穿著挺括的制服，攜帶著警徽和配槍，沒錯，羅尼的夢想是成為一名員警。對於羅尼的夢想，周圍的同時和朋友們都不以為然，尤其是漂亮的收銀員布蘭迪（安娜·法瑞絲 Anna Faris 飾），更是常常對羅尼這不切實際的夢想冷嘲熱諷。\n　　這一天，改變一切的機會到來了，一幫劫匪闖進了商場。得知消息的羅尼迅速在心裡打起了算盤，他打算親手逮捕這幫劫匪以彰顯自己“傑出的”員警天賦。然而，現實卻並沒有想像的那麼樂觀，羅尼莽撞的行為不僅為自己帶來了麻煩，同時也讓負責此案的警官哈里森（雷·利奧塔 Ray Liotta 飾）大為火光。夾在狡詐的劫匪和憤怒的員警之間，羅尼的情況可謂是千鈞一髮。\n\nMall security guard Ronnie Barnhardt is called into action to stop a flasher from turning shopper's paradise into his personal peep show. But when Barnhardt can't bring the culprit to justice, a surly police detective is recruited to close the case."
    },
    {
        "filename": "酷狗寶貝之復仇企鵝／超級無敵掌門狗：企鵝的復仇 Wallace & Gromit：Vengeance Most Fowl (2025) - 1080p.NF.WEB-DL.DDP5.1.Atmos.H.264-華堅馮力士.mp4",
        "absolute_path": "H:\\共用雲端硬碟\\@LiangTsaoEmby_本月更新\\電影\\酷狗寶貝之復仇企鵝／超級無敵掌門狗：企鵝的復仇 Wallace & Gromit：Vengeance Most Fowl (2025)\\酷狗寶貝之復仇企鵝／超級無敵掌門狗：企鵝的復仇 Wallace & Gromit：Vengeance Most Fowl (2025) - 1080p.NF.WEB-DL.DDP5.1.Atmos.H.264-華堅馮力士.mp4",
        "relative_path": "@LiangTsaoEmby_本月更新\\電影\\酷狗寶貝之復仇企鵝／超級無敵掌門狗：企鵝的復仇 Wallace & Gromit：Vengeance Most Fowl (2025)\\酷狗寶貝之復仇企鵝／超級無敵掌門狗：企鵝的復仇 Wallace & Gromit：Vengeance Most Fowl (2025) - 1080p.NF.WEB-DL.DDP5.1.Atmos.H.264-華堅馮力士.mp4",
        "timestamp": "2025-04-02T23:00:32.311731",
        "category": "movie",
        "tmdb_id": "929204",
        "tmdb_url": "https://www.themoviedb.org/movie/929204",
        "plot": "華力士的高科技發明開始任意妄為，華力士也被誣陷犯下各種可疑罪行，最棒的酷狗阿高立刻採取行動，拯救主人。"
    },
    {
        "filename": "酷玩樂隊：艾哈默德巴德現場 Coldplay Live in Ahmedabad (2025).mkv",
        "absolute_path": "H:\\共用雲端硬碟\\@LiangTsaoEmby_本月更新\\電影\\酷玩樂隊：艾哈默德巴德現場 Coldplay Live in Ahmedabad (2025)\\酷玩樂隊：艾哈默德巴德現場 Coldplay Live in Ahmedabad (2025).mkv",
        "relative_path": "@LiangTsaoEmby_本月更新\\電影\\酷玩樂隊：艾哈默德巴德現場 Coldplay Live in Ahmedabad (2025)\\酷玩樂隊：艾哈默德巴德現場 Coldplay Live in Ahmedabad (2025).mkv",
        "timestamp": "2025-04-02T23:00:42.325049",
        "category": "movie",
        "tmdb_id": "1431072",
        "tmdb_url": "https://www.themoviedb.org/movie/1431072",
        "plot": "Coldplay presents their iconic Music of the Spheres World Tour concert live from Ahmedabad, in their biggest ever concert."
    },
    {
        "filename": "慾情故縱／為何是你 Why Do You？ (2024).mkv",
        "absolute_path": "H:\\共用雲端硬碟\\@LiangTsaoEmby_本月更新\\電影\\慾情故縱／為何是你 Why Do You？ (2024)\\慾情故縱／為何是你 Why Do You？ (2024).mkv",
        "relative_path": "@LiangTsaoEmby_本月更新\\電影\\慾情故縱／為何是你 Why Do You？ (2024)\\慾情故縱／為何是你 Why Do You？ (2024).mkv",
        "timestamp": "2025-04-02T23:00:52.336480",
        "category": "movie",
        "tmdb_id": "1267217",
        "tmdb_url": "https://www.themoviedb.org/movie/1267217",
        "plot": "叛逆又熱情的大學生艾拉，為了反抗母親的控制，透過「乾爹」交友軟體意外邂逅了充滿魅力的已婚企業家安德烈，一夜情後挑起的慾望令她逐漸沉淪其中，兩人激情的痕跡遍及各處，一段錯誤的感情似乎也在悄悄滋長...。"
    },
    {
        "filename": "潛水 The Dive (2023) - 1080p.BluRay.x264.DTS-QuickIO.mkv",
        "absolute_path": "H:\\共用雲端硬碟\\@LiangTsaoEmby_本月更新\\電影\\潛水 The Dive (2023)\\潛水 The Dive (2023) - 1080p.BluRay.x264.DTS-QuickIO.mkv",
        "relative_path": "@LiangTsaoEmby_本月更新\\電影\\潛水 The Dive (2023)\\潛水 The Dive (2023) - 1080p.BluRay.x264.DTS-QuickIO.mkv",
        "timestamp": "2025-04-02T23:01:02.347517",
        "category": "movie",
        "tmdb_id": "1109534",
        "tmdb_url": "https://www.themoviedb.org/movie/1109534",
        "plot": "兩姐妹去一個美麗而偏遠的地方潛水。其中一名姐妹被巖石擊中，被困在 28 米深的地方。由於氧氣含量極低且氣溫寒冷，她的妹妹必須為自己的生命而戰。"
    },
    {
        "filename": "請別相信她 Too Beautiful To Lie (2023).mkv",
        "absolute_path": "H:\\共用雲端硬碟\\@LiangTsaoEmby_本月更新\\電影\\請別相信她 Too Beautiful To Lie (2023)\\請別相信她 Too Beautiful To Lie (2023).mkv",
        "relative_path": "@LiangTsaoEmby_本月更新\\電影\\請別相信她 Too Beautiful To Lie (2023)\\請別相信她 Too Beautiful To Lie (2023).mkv",
        "timestamp": "2025-04-02T23:01:12.355346",
        "category": "movie",
        "tmdb_id": "1079536",
        "tmdb_url": "https://www.themoviedb.org/movie/1079536",
        "plot": "「江湖女騙子」白娜（章若楠 飾）與「小鎮憨憨男」方耀東（吳昱翰 飾）在船上不打不相識，誰料冤家路窄白娜陰差陽錯竟被當成方耀東媳婦，受到方家人的熱情款待。而方耀東為了戳穿白娜謊言、贏回家人信任，與白娜鬥智鬥勇惹出笑料不斷，家庭保衞戰一觸即發，「女騙子」與「憨憨男」高手過招相愛相殺  。"
    },
    {
        "filename": "隱形猛禽 The Invisible Raptor (2024) - BluRay.1080p.DTS-HDMA5.1.x265.10bit-DreamHD.mkv",
        "absolute_path": "H:\\共用雲端硬碟\\@LiangTsaoEmby_本月更新\\電影\\隱形猛禽 The Invisible Raptor (2024)\\隱形猛禽 The Invisible Raptor (2024) - BluRay.1080p.DTS-HDMA5.1.x265.10bit-DreamHD.mkv",
        "relative_path": "@LiangTsaoEmby_本月更新\\電影\\隱形猛禽 The Invisible Raptor (2024)\\隱形猛禽 The Invisible Raptor (2024) - BluRay.1080p.DTS-HDMA5.1.x265.10bit-DreamHD.mkv",
        "timestamp": "2025-04-02T23:01:22.375833",
        "category": "movie",
        "tmdb_id": "1181212",
        "tmdb_url": "https://www.themoviedb.org/movie/1181212",
        "plot": "一位遊樂園古生物學家和一名倒楣的保全聯手阻止一隻看不見的猛禽對他們的小鎮造成嚴重破壞。"
    },
    {
        "filename": "邊境奇襲 Contraataque (2025).mkv",
        "absolute_path": "H:\\共用雲端硬碟\\@LiangTsaoEmby_本月更新\\電影\\邊境奇襲 Contraataque (2025)\\邊境奇襲 Contraataque (2025).mkv",
        "relative_path": "@LiangTsaoEmby_本月更新\\電影\\邊境奇襲 Contraataque (2025)\\邊境奇襲 Contraataque (2025).mkv",
        "timestamp": "2025-04-02T23:01:32.394307",
        "category": "movie",
        "tmdb_id": "1356039",
        "tmdb_url": "https://www.themoviedb.org/movie/1356039",
        "plot": "營救人質任務招來新敵人，格雷洛上尉和他率領的精銳士兵必須面對犯罪集團的伏擊。"
    },
    {
        "filename": "House.of.David.S01E07 - 4K.mkv",
        "absolute_path": "H:\\共用雲端硬碟\\@LiangTsaoEmby_本月更新\\連載中\\大衛王朝 House of David (2025)\\Season 01\\House.of.David.S01E07 - 4K.mkv",
        "relative_path": "@LiangTsaoEmby_本月更新\\連載中\\大衛王朝 House of David (2025)\\Season 01\\House.of.David.S01E07 - 4K.mkv",
        "timestamp": "2025-04-02T23:14:06.719397",
        "category": "tvshow",
        "tmdb_id": "243881",
        "tmdb_url": "https://www.themoviedb.org/tv/243881",
        "plot": "國王、英雄和反派們為爭奪王冠展開最後的對決。戰爭在所難免，在古老的戰場上，各方勢力在為一場決定以色列命運的宏大戰鬥做準備。"
    },
    {
        "filename": "The.White.Lotus.S03E07.mkv",
        "absolute_path": "H:\\共用雲端硬碟\\@LiangTsaoEmby_本月更新\\連載中\\白蓮花大飯店／白蓮花度假村 The White Lotus (2021)\\Season 03\\The.White.Lotus.S03E07.mkv",
        "relative_path": "@LiangTsaoEmby_本月更新\\連載中\\白蓮花大飯店／白蓮花度假村 The White Lotus (2021)\\Season 03\\The.White.Lotus.S03E07.mkv",
        "timestamp": "2025-04-02T23:15:53.248909",
        "category": "tvshow",
        "tmdb_id": "111803",
        "tmdb_url": "https://www.themoviedb.org/tv/111803",
        "plot": "貝琳達帶著賽昂參加克蘿伊的外國人派對。薩克森對蒂姆的怪異舉動提出質疑。蓋濤和珍珠準備第一次約會。"
    },
    {
        "filename": "Cinderella.Game.S01E77.2024.1080p.Viu.WEB-DL.H264.AAC-PanWEB.mkv",
        "absolute_path": "H:\\共用雲端硬碟\\@LiangTsaoEmby_本月更新\\連載中\\灰姑娘遊戲 신데렐라 게임 Cinderella Game (2024)\\Season 01\\Cinderella.Game.S01E77.2024.1080p.Viu.WEB-DL.H264.AAC-PanWEB.mkv",
        "relative_path": "@LiangTsaoEmby_本月更新\\連載中\\灰姑娘遊戲 신데렐라 게임 Cinderella Game (2024)\\Season 01\\Cinderella.Game.S01E77.2024.1080p.Viu.WEB-DL.H264.AAC-PanWEB.mkv",
        "timestamp": "2025-04-02T23:16:14.211002",
        "category": "tvshow",
        "tmdb_id": "275591",
        "tmdb_url": "https://www.themoviedb.org/tv/275591",
        "plot": "Jin-goo finds Se-young unconscious, so he takes her to the hospital. As soon as she wakes up, Se-young demands Jin-goo to take responsibility for her. Myung-ji suggests Yeo-jin send Eun-chong abroad to make him grow distant from Ha-na. Yeo-jin finally realizes who the Goo siblings are on the day of the company's external audit."
    },
    {
        "filename": "Cinderella.Game.S01E78.2024.1080p.Viu.WEB-DL.H264.AAC-PanWEB.mkv",
        "absolute_path": "H:\\共用雲端硬碟\\@LiangTsaoEmby_本月更新\\連載中\\灰姑娘遊戲 신데렐라 게임 Cinderella Game (2024)\\Season 01\\Cinderella.Game.S01E78.2024.1080p.Viu.WEB-DL.H264.AAC-PanWEB.mkv",
        "relative_path": "@LiangTsaoEmby_本月更新\\連載中\\灰姑娘遊戲 신데렐라 게임 Cinderella Game (2024)\\Season 01\\Cinderella.Game.S01E78.2024.1080p.Viu.WEB-DL.H264.AAC-PanWEB.mkv",
        "timestamp": "2025-04-02T23:16:25.231347",
        "category": "tvshow",
        "tmdb_id": "275591",
        "tmdb_url": "https://www.themoviedb.org/tv/275591",
        "plot": "Ha-na reveals that she's the chief auditor to Yeo-jin and that she's looking to take revenge. The news about Se-young's fake pregnancy breaks out, resulting in a boycott against Hyesung Group. Meanwhile, Yeo-jin sets up an appointment to meet Richard Han to solve the issue with the Goo siblings."
    },
    {
        "filename": "With.Love.With.You.S01E06 - 4K.mp4",
        "absolute_path": "H:\\共用雲端硬碟\\@LiangTsaoEmby_本月更新\\連載中\\有你的時光裡 With Love With You (2025)\\Season 01\\With.Love.With.You.S01E06 - 4K.mp4",
        "relative_path": "@LiangTsaoEmby_本月更新\\連載中\\有你的時光裡 With Love With You (2025)\\Season 01\\With.Love.With.You.S01E06 - 4K.mp4",
        "timestamp": "2025-04-02T23:16:57.759009",
        "category": "tvshow",
        "tmdb_id": "256887",
        "tmdb_url": "https://www.themoviedb.org/tv/256887",
        "plot": "王家兩姐妹自小性格迥異,姐姐王焱患先天性貧血癥,妹妹王靈均任性頑劣。王靈均不顧家人反對來到深 圳,打破了同在深圳的王焱的看似平靜的生活。失業的王靈均住進了王焱家裡,二人的相處從最初的雞飛狗跳逐漸變得 和諧溫馨起來,姐妹倆也慢慢收穫了屬於各自的感情。王焱舊病復發,曾一心想擺脫姐姐的王靈均選擇守護在她身邊。 在經歷了工作和生活風波后,王焱卸下了心理包袱,王靈均也放下了芥蒂,姐妹倆一起開啟了新的生活"
    },
    {
        "filename": "With.Love.With.You.S01E04 - 4K.mp4",
        "absolute_path": "H:\\共用雲端硬碟\\@LiangTsaoEmby_本月更新\\連載中\\有你的時光裡 With Love With You (2025)\\Season 01\\With.Love.With.You.S01E04 - 4K.mp4",
        "relative_path": "@LiangTsaoEmby_本月更新\\連載中\\有你的時光裡 With Love With You (2025)\\Season 01\\With.Love.With.You.S01E04 - 4K.mp4",
        "timestamp": "2025-04-02T23:17:07.784925",
        "category": "tvshow",
        "tmdb_id": "256887",
        "tmdb_url": "https://www.themoviedb.org/tv/256887",
        "plot": "王家兩姐妹自小性格迥異,姐姐王焱患先天性貧血癥,妹妹王靈均任性頑劣。王靈均不顧家人反對來到深 圳,打破了同在深圳的王焱的看似平靜的生活。失業的王靈均住進了王焱家裡,二人的相處從最初的雞飛狗跳逐漸變得 和諧溫馨起來,姐妹倆也慢慢收穫了屬於各自的感情。王焱舊病復發,曾一心想擺脫姐姐的王靈均選擇守護在她身邊。 在經歷了工作和生活風波后,王焱卸下了心理包袱,王靈均也放下了芥蒂,姐妹倆一起開啟了新的生活"
    },
    {
        "filename": "With.Love.With.You.S01E05 - 4K.mp4",
        "absolute_path": "H:\\共用雲端硬碟\\@LiangTsaoEmby_本月更新\\連載中\\有你的時光裡 With Love With You (2025)\\Season 01\\With.Love.With.You.S01E05 - 4K.mp4",
        "relative_path": "@LiangTsaoEmby_本月更新\\連載中\\有你的時光裡 With Love With You (2025)\\Season 01\\With.Love.With.You.S01E05 - 4K.mp4",
        "timestamp": "2025-04-02T23:17:17.818784",
        "category": "tvshow",
        "tmdb_id": "256887",
        "tmdb_url": "https://www.themoviedb.org/tv/256887",
        "plot": "王家兩姐妹自小性格迥異,姐姐王焱患先天性貧血癥,妹妹王靈均任性頑劣。王靈均不顧家人反對來到深 圳,打破了同在深圳的王焱的看似平靜的生活。失業的王靈均住進了王焱家裡,二人的相處從最初的雞飛狗跳逐漸變得 和諧溫馨起來,姐妹倆也慢慢收穫了屬於各自的感情。王焱舊病復發,曾一心想擺脫姐姐的王靈均選擇守護在她身邊。 在經歷了工作和生活風波后,王焱卸下了心理包袱,王靈均也放下了芥蒂,姐妹倆一起開啟了新的生活"
    },
    {
        "filename": "With.Love.With.You.S01E03 - 4K.mp4",
        "absolute_path": "H:\\共用雲端硬碟\\@LiangTsaoEmby_本月更新\\連載中\\有你的時光裡 With Love With You (2025)\\Season 01\\With.Love.With.You.S01E03 - 4K.mp4",
        "relative_path": "@LiangTsaoEmby_本月更新\\連載中\\有你的時光裡 With Love With You (2025)\\Season 01\\With.Love.With.You.S01E03 - 4K.mp4",
        "timestamp": "2025-04-02T23:17:27.838168",
        "category": "tvshow",
        "tmdb_id": "256887",
        "tmdb_url": "https://www.themoviedb.org/tv/256887",
        "plot": "王家兩姐妹自小性格迥異,姐姐王焱患先天性貧血癥,妹妹王靈均任性頑劣。王靈均不顧家人反對來到深 圳,打破了同在深圳的王焱的看似平靜的生活。失業的王靈均住進了王焱家裡,二人的相處從最初的雞飛狗跳逐漸變得 和諧溫馨起來,姐妹倆也慢慢收穫了屬於各自的感情。王焱舊病復發,曾一心想擺脫姐姐的王靈均選擇守護在她身邊。 在經歷了工作和生活風波后,王焱卸下了心理包袱,王靈均也放下了芥蒂,姐妹倆一起開啟了新的生活"
    },
    {
        "filename": "With.Love.With.You.S01E01 - 4K.mp4",
        "absolute_path": "H:\\共用雲端硬碟\\@LiangTsaoEmby_本月更新\\連載中\\有你的時光裡 With Love With You (2025)\\Season 01\\With.Love.With.You.S01E01 - 4K.mp4",
        "relative_path": "@LiangTsaoEmby_本月更新\\連載中\\有你的時光裡 With Love With You (2025)\\Season 01\\With.Love.With.You.S01E01 - 4K.mp4",
        "timestamp": "2025-04-02T23:17:37.868224",
        "category": "tvshow",
        "tmdb_id": "256887",
        "tmdb_url": "https://www.themoviedb.org/tv/256887",
        "plot": "王家兩姐妹自小性格迥異,姐姐王焱患先天性貧血癥,妹妹王靈均任性頑劣。王靈均不顧家人反對來到深 圳,打破了同在深圳的王焱的看似平靜的生活。失業的王靈均住進了王焱家裡,二人的相處從最初的雞飛狗跳逐漸變得 和諧溫馨起來,姐妹倆也慢慢收穫了屬於各自的感情。王焱舊病復發,曾一心想擺脫姐姐的王靈均選擇守護在她身邊。 在經歷了工作和生活風波后,王焱卸下了心理包袱,王靈均也放下了芥蒂,姐妹倆一起開啟了新的生活"
    },
    {
        "filename": "With.Love.With.You.S01E02 - 4K.mp4",
        "absolute_path": "H:\\共用雲端硬碟\\@LiangTsaoEmby_本月更新\\連載中\\有你的時光裡 With Love With You (2025)\\Season 01\\With.Love.With.You.S01E02 - 4K.mp4",
        "relative_path": "@LiangTsaoEmby_本月更新\\連載中\\有你的時光裡 With Love With You (2025)\\Season 01\\With.Love.With.You.S01E02 - 4K.mp4",
        "timestamp": "2025-04-02T23:17:47.895373",
        "category": "tvshow",
        "tmdb_id": "256887",
        "tmdb_url": "https://www.themoviedb.org/tv/256887",
        "plot": "王家兩姐妹自小性格迥異,姐姐王焱患先天性貧血癥,妹妹王靈均任性頑劣。王靈均不顧家人反對來到深 圳,打破了同在深圳的王焱的看似平靜的生活。失業的王靈均住進了王焱家裡,二人的相處從最初的雞飛狗跳逐漸變得 和諧溫馨起來,姐妹倆也慢慢收穫了屬於各自的感情。王焱舊病復發,曾一心想擺脫姐姐的王靈均選擇守護在她身邊。 在經歷了工作和生活風波后,王焱卸下了心理包袱,王靈均也放下了芥蒂,姐妹倆一起開啟了新的生活"
    },
    {
        "filename": "With.Love.With.You.S01E08 - 4K.mp4",
        "absolute_path": "H:\\共用雲端硬碟\\@LiangTsaoEmby_本月更新\\連載中\\有你的時光裡 With Love With You (2025)\\Season 01\\With.Love.With.You.S01E08 - 4K.mp4",
        "relative_path": "@LiangTsaoEmby_本月更新\\連載中\\有你的時光裡 With Love With You (2025)\\Season 01\\With.Love.With.You.S01E08 - 4K.mp4",
        "timestamp": "2025-04-02T23:17:57.922110",
        "category": "tvshow",
        "tmdb_id": "256887",
        "tmdb_url": "https://www.themoviedb.org/tv/256887",
        "plot": "王家兩姐妹自小性格迥異,姐姐王焱患先天性貧血癥,妹妹王靈均任性頑劣。王靈均不顧家人反對來到深 圳,打破了同在深圳的王焱的看似平靜的生活。失業的王靈均住進了王焱家裡,二人的相處從最初的雞飛狗跳逐漸變得 和諧溫馨起來,姐妹倆也慢慢收穫了屬於各自的感情。王焱舊病復發,曾一心想擺脫姐姐的王靈均選擇守護在她身邊。 在經歷了工作和生活風波后,王焱卸下了心理包袱,王靈均也放下了芥蒂,姐妹倆一起開啟了新的生活"
    },
    {
        "filename": "With.Love.With.You.S01E07 - 4K.mp4",
        "absolute_path": "H:\\共用雲端硬碟\\@LiangTsaoEmby_本月更新\\連載中\\有你的時光裡 With Love With You (2025)\\Season 01\\With.Love.With.You.S01E07 - 4K.mp4",
        "relative_path": "@LiangTsaoEmby_本月更新\\連載中\\有你的時光裡 With Love With You (2025)\\Season 01\\With.Love.With.You.S01E07 - 4K.mp4",
        "timestamp": "2025-04-02T23:18:07.943977",
        "category": "tvshow",
        "tmdb_id": "256887",
        "tmdb_url": "https://www.themoviedb.org/tv/256887",
        "plot": "王家兩姐妹自小性格迥異,姐姐王焱患先天性貧血癥,妹妹王靈均任性頑劣。王靈均不顧家人反對來到深 圳,打破了同在深圳的王焱的看似平靜的生活。失業的王靈均住進了王焱家裡,二人的相處從最初的雞飛狗跳逐漸變得 和諧溫馨起來,姐妹倆也慢慢收穫了屬於各自的感情。王焱舊病復發,曾一心想擺脫姐姐的王靈均選擇守護在她身邊。 在經歷了工作和生活風波后,王焱卸下了心理包袱,王靈均也放下了芥蒂,姐妹倆一起開啟了新的生活"
    },
    {
        "filename": "With.Love.With.You.S01E10 - 4K.mp4",
        "absolute_path": "H:\\共用雲端硬碟\\@LiangTsaoEmby_本月更新\\連載中\\有你的時光裡 With Love With You (2025)\\Season 01\\With.Love.With.You.S01E10 - 4K.mp4",
        "relative_path": "@LiangTsaoEmby_本月更新\\連載中\\有你的時光裡 With Love With You (2025)\\Season 01\\With.Love.With.You.S01E10 - 4K.mp4",
        "timestamp": "2025-04-02T23:18:17.965904",
        "category": "tvshow",
        "tmdb_id": "256887",
        "tmdb_url": "https://www.themoviedb.org/tv/256887",
        "plot": "王家兩姐妹自小性格迥異,姐姐王焱患先天性貧血癥,妹妹王靈均任性頑劣。王靈均不顧家人反對來到深 圳,打破了同在深圳的王焱的看似平靜的生活。失業的王靈均住進了王焱家裡,二人的相處從最初的雞飛狗跳逐漸變得 和諧溫馨起來,姐妹倆也慢慢收穫了屬於各自的感情。王焱舊病復發,曾一心想擺脫姐姐的王靈均選擇守護在她身邊。 在經歷了工作和生活風波后,王焱卸下了心理包袱,王靈均也放下了芥蒂,姐妹倆一起開啟了新的生活"
    },
    {
        "filename": "With.Love.With.You.S01E09 - 4K.mp4",
        "absolute_path": "H:\\共用雲端硬碟\\@LiangTsaoEmby_本月更新\\連載中\\有你的時光裡 With Love With You (2025)\\Season 01\\With.Love.With.You.S01E09 - 4K.mp4",
        "relative_path": "@LiangTsaoEmby_本月更新\\連載中\\有你的時光裡 With Love With You (2025)\\Season 01\\With.Love.With.You.S01E09 - 4K.mp4",
        "timestamp": "2025-04-02T23:18:27.988092",
        "category": "tvshow",
        "tmdb_id": "256887",
        "tmdb_url": "https://www.themoviedb.org/tv/256887",
        "plot": "王家兩姐妹自小性格迥異,姐姐王焱患先天性貧血癥,妹妹王靈均任性頑劣。王靈均不顧家人反對來到深 圳,打破了同在深圳的王焱的看似平靜的生活。失業的王靈均住進了王焱家裡,二人的相處從最初的雞飛狗跳逐漸變得 和諧溫馨起來,姐妹倆也慢慢收穫了屬於各自的感情。王焱舊病復發,曾一心想擺脫姐姐的王靈均選擇守護在她身邊。 在經歷了工作和生活風波后,王焱卸下了心理包袱,王靈均也放下了芥蒂,姐妹倆一起開啟了新的生活"
    }
]